smolpub/__init__.py
smolpub/__main__.py
smolpub/app.py
smolpub-1.0.3.dist-info/METADATA
smolpub-1.0.3.dist-info/WHEEL
smolpub-1.0.3.dist-info/entry_points.txt
smolpub-1.0.3.dist-info/RECORD
