Metadata-Version: 2.1
Name: smolpub
Version: 1.0.3
Summary: A script that allows to post a text file to https://smol.pub
Home-page: https://github.com/fmaida/smol.pub
License: MIT
Author: Francesco Maida
Author-email: francesco.maida@gmail.com
Maintainer: Francesco Maida
Maintainer-email: francesco.maida@gmail.com
Requires-Python: >=3.11,<4.0
Classifier: License :: OSI Approved :: MIT License
Classifier: Programming Language :: Python :: 3
Classifier: Programming Language :: Python :: 3.11
Classifier: Programming Language :: Python :: 3.12
Requires-Dist: requests (>=2.32.3,<3.0.0)
Project-URL: Repository, https://github.com/fmaida/smol.pub
